kv_database_replit/__init__.py
keyvalue_database_replit-0.0.1.dist-info/LICENSE.txt
keyvalue_database_replit-0.0.1.dist-info/METADATA
keyvalue_database_replit-0.0.1.dist-info/WHEEL
keyvalue_database_replit-0.0.1.dist-info/top_level.txt
keyvalue_database_replit-0.0.1.dist-info/RECORD
