Metadata-Version: 2.1
Name: keyvalue-database-replit
Version: 0.0.1
Summary: Key Value DataBase
Home-page: UNKNOWN
Author: Miguel Merheb/ Ahmad Zaaroura
Author-email: ahmad.zaaroura.123@gmail.com
License: MIT
Keywords: DataBase
Platform: UNKNOWN
Classifier: Programming Language :: Python :: 3
Classifier: License :: OSI Approved :: MIT License
Classifier: Operating System :: OS Independent
Requires-Python: >=3.6
